{"title":"BIG WET BUTTS - Alena Croft - Alena Croft: The Notorious B.O.O.T","uid":11848449,"size":421894780,"categoryP":"porn","categoryS":"movie_clips","magnet":"?xt=urn:btih:017fb336a9b3569e2d1c76492bb5fdf63055c5c3&amp;dn=BIG+WET+BUTTS+-+Alena+Croft+-+Alena+Croft%3A+The+Notorious+B.O.O.T&amp;tr=udp%3A%2F%2Ftracker.openbittorrent.com%3A80&amp;tr=udp%3A%2F%2Fopen.demonii.com%3A1337&amp;tr=udp%3A%2F%2Ftracker.coppersurfer.tk%3A6969&amp;tr=udp%3A%2F%2Fexodus.desync.com%3A6969","seeders":2,"leechers":4,"uploader":"manam69","files":1,"time":1430029287,"description":"BIG WET BUTTS - Alena Croft - Alena Croft: The Notorious B.O.O.T.Y - NEW 26 APRIL 2015 NEW\n\nAlena Croft is back for some more dick, but this time she's taking things to the next level with her first anal on film! After Alena teases and squeezes for your viewing pleasure, she strips and starts the main event by stroking and sucking Mick Blue's big dick. Mick plunges deep into her big wet butt, giving her the kind of anal fucking you can only get from the big dicks right here at Brazzers. Check out the action as Alena cums all over Mick's cock over and over again, finally taking a big fat facial cumshot to cap off her very first anal scene ever!\n &lt;a href=&quot;\nhttp://s20.postimg.org/78t6ndwzh/image.jpg&quot; rel=&quot;nofollow&quot; target=&quot;_NEW&quot;&gt;\nhttp://s20.postimg.org/78t6ndwzh/image.jpg&lt;/a&gt;\n &lt;a href=&quot;\nhttp://s20.postimg.org/k1hanb8l9/bwb_alena_croft.jpg&quot; rel=&quot;nofollow&quot; target=&quot;_NEW&quot;&gt;\nhttp://s20.postimg.org/k1hanb8l9/bwb_alena_croft.jpg&lt;/a&gt;","torrent":{"xt":"urn:btih:017fb336a9b3569e2d1c76492bb5fdf63055c5c3","amp;dn":"BIG+WET+BUTTS+-+Alena+Croft+-+Alena+Croft%3A+The+Notorious+B.O.O.T","amp;tr":["udp%3A%2F%2Ftracker.openbittorrent.com%3A80","udp%3A%2F%2Fopen.demonii.com%3A1337","udp%3A%2F%2Ftracker.coppersurfer.tk%3A6969","udp%3A%2F%2Fexodus.desync.com%3A6969"],"infoHash":"017fb336a9b3569e2d1c76492bb5fdf63055c5c3","infoHashBuffer":{"type":"Buffer","data":[1,127,179,54,169,179,86,158,45,28,118,73,43,181,253,246,48,85,197,195]},"announce":[],"urlList":[]}}