{"title":"M.O.P. feat. Mobb Deep - Street Certified {Single-2014}","uid":9569282,"size":11294655,"categoryP":"audio","categoryS":"music","magnet":"?xt=urn:btih:02a0c90db97121eddea1bdc5902c052ee9276f2b&amp;dn=M.O.P.+feat.+Mobb+Deep+-+Street+Certified+%7BSingle-2014%7D&amp;tr=udp%3A%2F%2Ftracker.openbittorrent.com%3A80&amp;tr=udp%3A%2F%2Fopen.demonii.com%3A1337&amp;tr=udp%3A%2F%2Ftracker.coppersurfer.tk%3A6969&amp;tr=udp%3A%2F%2Fexodus.desync.com%3A6969","seeders":2,"leechers":0,"uploader":"MinTRoX","files":1,"time":1391596224,"description":"Format : MPEG Audio\nFile size : 10.8 MiB\nDuration : 4mn 39s\nOverall bit rate mode : Constant\nOverall bit rate : 320 Kbps\nAlbum : Street Certified (feat. Mobb Deep) - Single\nAlbum/Performer : M.O.P.\nTrack name : Street Certified\nTrack name/Position : 1\nPerformer : M.O.P. feat. Mobb Deep\nComposer : M.O.P.\nGenre : Hip-Hop/Rap\nRecorded date : 2014\nWriting library : LAME3.96.1\nCover : Yes\nCover type : Cover (front)\nCover MIME : image/jpg\n\nAudio\nFormat : MPEG Audio\nFormat version : Version 1\nFormat profile : Layer 3\nMode : Joint stereo\nDuration : 4mn 40s\nBit rate mode : Constant\nBit rate : 320 Kbps\nChannel count : 2 channels\nSampling rate : 44.1 KHz\nCompression mode : Lossy\nStream size : 10.7 MiB (99%)\nWriting library : LAME3.96.1","torrent":{"xt":"urn:btih:02a0c90db97121eddea1bdc5902c052ee9276f2b","amp;dn":"M.O.P.+feat.+Mobb+Deep+-+Street+Certified+%7BSingle-2014%7D","amp;tr":["udp%3A%2F%2Ftracker.openbittorrent.com%3A80","udp%3A%2F%2Fopen.demonii.com%3A1337","udp%3A%2F%2Ftracker.coppersurfer.tk%3A6969","udp%3A%2F%2Fexodus.desync.com%3A6969"],"infoHash":"02a0c90db97121eddea1bdc5902c052ee9276f2b","infoHashBuffer":{"type":"Buffer","data":[2,160,201,13,185,113,33,237,222,161,189,197,144,44,5,46,233,39,111,43]},"announce":[],"urlList":[]}}