{"title":"Libro.El.Buen.Sexo","uid":5406960,"size":2878028,"categoryP":"other","categoryS":"e_books","magnet":"?xt=urn:btih:04b5b601438e365cf3cd178b663e6a67982ae88b&amp;dn=Libro.El.Buen.Sexo&amp;tr=udp%3A%2F%2Ftracker.openbittorrent.com%3A80&amp;tr=udp%3A%2F%2Fopen.demonii.com%3A1337&amp;tr=udp%3A%2F%2Ftracker.coppersurfer.tk%3A6969&amp;tr=udp%3A%2F%2Fexodus.desync.com%3A6969","seeders":3,"leechers":0,"uploader":"furtaperas","files":1,"time":1267631794,"description":"Los cambios en la percepciÃƒÂ³n y experiencia de la sexualidad han sido especialmente intensos en los ÃƒÂºltimos cincuenta aÃƒÂ±os. Estamos confluyendo en un proceso unitario, compartiendo consensos como: igualdad de gÃƒÂ©nero, tolerancia y respeto para la diversidad de opciones, felicidad y placer sexual como un derecho humano, libre elecciÃƒÂ³n de pareja, prevenciÃƒÂ³n y sexo seguro. En las siguientes pÃƒÂ¡ginas conocerÃƒÂ¡n el aspecto positivo del proceso de cambio cultural respecto del sexo. Esta transformaciÃƒÂ³n ocurre simultÃƒÂ¡neamente con la realidad de frustraciÃƒÂ³n y violencia sexual que entristece y descarga a miles de personas, dificultando seriamente sus posibilidades de autorrealizaciÃƒÂ³n y de establecer relaciones y convivencias positivas.","torrent":{"xt":"urn:btih:04b5b601438e365cf3cd178b663e6a67982ae88b","amp;dn":"Libro.El.Buen.Sexo","amp;tr":["udp%3A%2F%2Ftracker.openbittorrent.com%3A80","udp%3A%2F%2Fopen.demonii.com%3A1337","udp%3A%2F%2Ftracker.coppersurfer.tk%3A6969","udp%3A%2F%2Fexodus.desync.com%3A6969"],"infoHash":"04b5b601438e365cf3cd178b663e6a67982ae88b","infoHashBuffer":{"type":"Buffer","data":[4,181,182,1,67,142,54,92,243,205,23,139,102,62,106,103,152,42,232,139]},"announce":[],"urlList":[]}}