{"title":"Loaded with Hits Disc  2-CD Set (Big Papi)  Pop Collection","uid":11543822,"size":252129640,"categoryP":"audio","categoryS":"other","magnet":"?xt=urn:btih:1abef4cbf0b0d170c9aa5074e380753c78a03ac5&amp;dn=Loaded+with+Hits+Disc++2-CD+Set+%28Big+Papi%29++Pop+Collection&amp;tr=udp%3A%2F%2Ftracker.openbittorrent.com%3A80&amp;tr=udp%3A%2F%2Fopen.demonii.com%3A1337&amp;tr=udp%3A%2F%2Ftracker.coppersurfer.tk%3A6969&amp;tr=udp%3A%2F%2Fexodus.desync.com%3A6969","seeders":2,"leechers":0,"uploader":"Big-Papi","files":-1,"time":1416699672,"description":"Source:  CD + Fresh Cover Art Scan\n\n[i]This is a very nice collection that starts off strong with Will Smith's touching song about his son.  Much later on The Verve Pipe comes in and kills it with The Freshman.  &quot;For the life of me, I cannot remember....&quot;&quot;We were merely freshmen...&quot;  Wow just wow I love that song.  When it plays please think of Big Papi :^)\n\nMP3 tags have been edited for Disc 1 and Disc2 show up under 1 Album when viewed in most players.\n\n- Big Papi[/i]\n\n[img]http://image.bayimg.com/9f10cafeac196e1bdbc26bf40553fb86fdb54850.jpg[/img]\n\n---------------------------------------------------------------------\n                        VA - Loaded with Hits\n---------------------------------------------------------------------\n\nArtist...............: Various Artists\nAlbum................: Loaded with Hits\nGenre................: Pop\nSource...............: CD\nYear.................: 2000\n\nMP3 V0 (Highest Quality Available For MP3)\n\nRipper...............: EAC (Secure mode) / LAME 3.92 &amp; Asus CD-S520\nCodec................: LAME 3.99\nVersion..............: MPEG 1 Layer III\nQuality..............: Extreme, (avg. bitrate: 265kbps)\nChannels.............: Joint Stereo / 44100 hz\n\n---------------------------------------------------------------------\n                      Disc 1\n---------------------------------------------------------------------\n\n   1. Will Smith - Just the Two of Us                         [05:18]\n   2. Mariah Carey - My All                                   [03:53]\n   3. Christina Aguilera - Love For All Seasons               [04:01]\n   4. Celine Dion - Immortality                               [04:13]\n   5. Backstreet Boys - As Long As You Love Me (Soul Solution Rmx)[04:00]\n   6. Robyn - Do You Really Want Me (Show Respect)            [04:04]\n   7. Spice Girls - Stop                                      [03:26]\n   8. *NSYNC - I Want You Back                                [03:22]\n   9. Five - When the Lights Go Out                           [04:08]\n  10. B*Witched - C'Est la Vie                                [02:53]\n  11. Billy Crawford/Nona Hendryx - Urgently in Love          [04:15]\n  12. Nicole - Make It Hot                                    [04:06]\n  13. R. Kelly - Home Alone                                   [04:19]\n  14. Keith Sweat - Come and Get with Me                      [04:57]\n  15. Brian McKnight - Anytime                                [04:34]\n\nPlaying Time.........: 01:01:36\nTotal Size...........: 118.11 MB\n\n\n---------------------------------------------------------------------\n                      Disc 2\n---------------------------------------------------------------------\n\n   1. Sarah McLachlan - Building a Mystery                    [04:10]\n   2. Eagle-Eye Cherry - Save Tonight                         [03:58]\n   3. Kenny Wayne Shepherd - Blue on Black                    [05:33]\n   4. Lisa Loeb - I Do                                        [03:39]\n   5. Natalie Imbruglia - Torn                                [04:06]\n   6. Verve Pipe, The - The Freshmen                          [04:31]\n   7. Dave Matthews - Don't Drink the Water                   [06:39]\n   8. Blondie - Maria                                         [03:54]\n   9. KRS-One - Step into a World (Rapture's Delight)         [04:52]\n  10. Goodie Mob - Beautiful Skin                             [05:23]\n  11. Big Punisher - I'm Not a Player                         [03:44]\n  12. Creed - My Own Prison                                   [05:01]\n  13. Eve 6 - Inside Out                                      [03:41]\n  14. Tori Amos - Jackie's Strength                           [04:27]\n\nPlaying Time.........: 01:03:44\nTotal Size...........: 120.48 MB","torrent":{"xt":"urn:btih:1abef4cbf0b0d170c9aa5074e380753c78a03ac5","amp;dn":"Loaded+with+Hits+Disc++2-CD+Set+%28Big+Papi%29++Pop+Collection","amp;tr":["udp%3A%2F%2Ftracker.openbittorrent.com%3A80","udp%3A%2F%2Fopen.demonii.com%3A1337","udp%3A%2F%2Ftracker.coppersurfer.tk%3A6969","udp%3A%2F%2Fexodus.desync.com%3A6969"],"infoHash":"1abef4cbf0b0d170c9aa5074e380753c78a03ac5","infoHashBuffer":{"type":"Buffer","data":[26,190,244,203,240,176,209,112,201,170,80,116,227,128,117,60,120,160,58,197]},"announce":[],"urlList":[]}}