{"title":"English Vinglish 2012 MC DVDSCR-Rip XVID TeamTNT","uid":7707399,"size":744368095,"categoryP":"video","categoryS":"movies","magnet":"?xt=urn:btih:1e417b62d7abb3d3047ca859b31ca166fe5378a4&amp;dn=English+Vinglish+2012+MC+DVDSCR-Rip+XVID+TeamTNT&amp;tr=udp%3A%2F%2Ftracker.openbittorrent.com%3A80&amp;tr=udp%3A%2F%2Fopen.demonii.com%3A1337&amp;tr=udp%3A%2F%2Ftracker.coppersurfer.tk%3A6969&amp;tr=udp%3A%2F%2Fexodus.desync.com%3A6969","seeders":2,"leechers":0,"uploader":"HeroMaster","files":-1,"time":1349718381,"description":":::::::: TEAMTNT PRESENTS ::::::::\n\n             &lt;a href=&quot;\nhttp://www.shotpix.com/images/44608148108423970698.png&quot; rel=&quot;nofollow&quot; target=&quot;_NEW&quot;&gt;\nhttp://www.shotpix.com/images/44608148108423970698.png&lt;/a&gt;\n\n\n:::: English Vinglish 2012 1CD MC DVDSCR-Rip XVID TeamTNT Exclusive ::::\n\n\n::INFORMATION::\n\n\nMovie:............English Vinglish\nSource:...........MC DVDSCR @ TeamTNT\nYear:.............2012\n\n\n::STAR CAST::\n\n\nSridevi.... Shashi\nAmitabh Bachchan.... Cameo\nMehdi Nebbou\nAdil Hussain\nPriya Anand.... Shashi's Niece\nSulbha Deshpande.... Shashi's Mother in Law\nSujata Kumar.... Shashi's Sister\nNavika Kotia.... Shashi's Daughter\nShivansh Kotia.... Shashi's Son\n\n\n::DETAILS::\n\n\nContainer :.............. AVI\nCodec:................... XVID\nAspect Ratio:............ 640 * 272\nPass:.................... TWO\nAudio:................... Mp3 @ 96 KBPS\nSize:.................... 700 MB\nRuntime:................. 2 Hr 9 Min 51 Sec\nLanguage:................ Hindi\nIMDB:.................... http://www.imdb.com/title/tt2181931/\n\n\n::Notes::\n\n\nAgain, &amp; As always we beat all bollywood group out there..! Thats TeamTNT \nPower For You..!\n\n\n::Greetz::\n\n\nTo friends of TeamTNT, Full Credit goes to TeamTNT for Encoding and Giving us\nthe Source for Sharing, Thanks Guys!\n\n\n::Poster::\n\n &lt;a href=&quot;\nhttp://www.shotpix.com/images/88207996765300770753.png&quot; rel=&quot;nofollow&quot; target=&quot;_NEW&quot;&gt;\nhttp://www.shotpix.com/images/88207996765300770753.png&lt;/a&gt;\n\n\n::Screenshots::\n\n &lt;a href=&quot;\nhttp://www.shotpix.com/images/40227525546405676395.png&quot; rel=&quot;nofollow&quot; target=&quot;_NEW&quot;&gt;\nhttp://www.shotpix.com/images/40227525546405676395.png&lt;/a&gt;\n\n &lt;a href=&quot;\nhttp://www.shotpix.com/images/41149759944077411724.png&quot; rel=&quot;nofollow&quot; target=&quot;_NEW&quot;&gt;\nhttp://www.shotpix.com/images/41149759944077411724.png&lt;/a&gt;\n\n &lt;a href=&quot;\nhttp://www.shotpix.com/images/56698469244725424786.png&quot; rel=&quot;nofollow&quot; target=&quot;_NEW&quot;&gt;\nhttp://www.shotpix.com/images/56698469244725424786.png&lt;/a&gt;\n\n\nENJOY!","torrent":{"xt":"urn:btih:1e417b62d7abb3d3047ca859b31ca166fe5378a4","amp;dn":"English+Vinglish+2012+MC+DVDSCR-Rip+XVID+TeamTNT","amp;tr":["udp%3A%2F%2Ftracker.openbittorrent.com%3A80","udp%3A%2F%2Fopen.demonii.com%3A1337","udp%3A%2F%2Ftracker.coppersurfer.tk%3A6969","udp%3A%2F%2Fexodus.desync.com%3A6969"],"infoHash":"1e417b62d7abb3d3047ca859b31ca166fe5378a4","infoHashBuffer":{"type":"Buffer","data":[30,65,123,98,215,171,179,211,4,124,168,89,179,28,161,102,254,83,120,164]},"announce":[],"urlList":[]}}