{"title":"VA Living The Blues Louisiana Blues Classics 1999 FLAC+CUE [RLG]","uid":11456248,"size":235692790,"categoryP":"audio","categoryS":"flac","magnet":"?xt=urn:btih:22d51a87aab4875378c4e8a3f71073c7dc7d5738&amp;dn=VA+Living+The+Blues+Louisiana+Blues+Classics+1999+FLAC%2BCUE+%5BRLG%5D&amp;tr=udp%3A%2F%2Ftracker.openbittorrent.com%3A80&amp;tr=udp%3A%2F%2Fopen.demonii.com%3A1337&amp;tr=udp%3A%2F%2Ftracker.coppersurfer.tk%3A6969&amp;tr=udp%3A%2F%2Fexodus.desync.com%3A6969","seeders":3,"leechers":0,"uploader":"RedLegsGreaves","files":-1,"time":1415938105,"description":"1 Smiley Lewis - I Hear You Knocking 2:44\n2 Professor Longhair - Go to the Mardi Gras 2:50\n3 Fats Domino - Going to the River 2:31\n4 Lloyd Price - Tell Me Pretty Baby 2:19\n5 Guitar Slim - It Hurts to Love Someone 2:41\n6 Lonesome Sundown - My Home Is a Prison 3:11\n7 Art Neville - Cha Dooky Doo 2:39\n8 Champion Jack Dupree - Blues for Everybody 2:36\n9 Wee Willie Wayne Travelin' Mood 2:30\n10 Archibald - Stack-A-Lee, Parts 1 &amp; 2 1:40\n11 Rockin' Sidney - You Ain't Nothin' but Fine 3:23\n12 Lazy Lester - They Call Me Lazy \n13 Irma Thomas - Don't Mess With My Man 2:22\n14 Clifton Chenier - My Soul 2:55\n15 Chris Kenner\t- Sick and Tired 2:33\n16 Slim Harpo - Tip on In, Part 1 2:53\n17 Cleveland Crochet - Sugar Bee 2:33\n18 Katie Webster &amp; Ashton Conroy - No Bread, No Meat 2:33\n19 Earl King - Trick Bag 2:48\n20 Bobby Marchan - There Is Something on Your Mind\n\n\n\nExact Audio Copy V1.0 beta 3 from 29. August 2011\n\nEAC extraction logfile from 11. November 2014, 20:53\n\nLiving The Blues - Louisiana Blues Classics / Living The Blues - Louisiana Blues Classics\n\nUsed drive  : TSSTcorpCDDVDW SH-S222A   Adapter: 1  ID: 0\n\nRead mode               : Secure\nUtilize accurate stream : Yes\nDefeat audio cache      : Yes\nMake use of C2 pointers : No\n\nRead offset correction                      : 6\nOverread into Lead-In and Lead-Out          : No\nFill up missing offset samples with silence : Yes\nDelete leading and trailing silent blocks   : No\nNull samples used in CRC calculations       : Yes\nUsed interface                              : Native Win32 interface for Win NT &amp; 2000\nGap handling                                : Appended to previous track\n\nUsed output format              : User Defined Encoder\nSelected bitrate                : 768 kBit/s\nQuality                         : High\nAdd ID3 tag                     : No\n\n\n\nAudio\nFormat                                   : FLAC\nFormat/Info                              : Free Lossless Audio Codec\nDuration                                 : 2mn 44s\nBit rate mode                            : Variable\nBit rate                                 : 405 Kbps\nChannel(s)                               : 2 channels\nSampling rate                            : 44.1 KHz\nBit depth                                : 16 bits\nStream size                              : 7.95 MiB (100%)\nWriting library                          : libFLAC 1.2.1 (UTC 2007-09-17)","torrent":{"xt":"urn:btih:22d51a87aab4875378c4e8a3f71073c7dc7d5738","amp;dn":"VA+Living+The+Blues+Louisiana+Blues+Classics+1999+FLAC%2BCUE+%5BRLG%5D","amp;tr":["udp%3A%2F%2Ftracker.openbittorrent.com%3A80","udp%3A%2F%2Fopen.demonii.com%3A1337","udp%3A%2F%2Ftracker.coppersurfer.tk%3A6969","udp%3A%2F%2Fexodus.desync.com%3A6969"],"infoHash":"22d51a87aab4875378c4e8a3f71073c7dc7d5738","infoHashBuffer":{"type":"Buffer","data":[34,213,26,135,170,180,135,83,120,196,232,163,247,16,115,199,220,125,87,56]},"announce":[],"urlList":[]}}