{"title":"Lady Suzanne----10 Minutes JOI Game.mp4","uid":10020585,"size":71658162,"categoryP":"porn","categoryS":"movie_clips","magnet":"?xt=urn:btih:2d9b8067d85436630616af33ce778bc67c4bc0f0&amp;dn=Lady+Suzanne%5C----10+Minutes+JOI+Game.mp4&amp;tr=udp%3A%2F%2Ftracker.openbittorrent.com%3A80&amp;tr=udp%3A%2F%2Fopen.demonii.com%3A1337&amp;tr=udp%3A%2F%2Ftracker.coppersurfer.tk%3A6969&amp;tr=udp%3A%2F%2Fexodus.desync.com%3A6969","seeders":3,"leechers":0,"uploader":"merzedes","files":-1,"time":1398203626,"description":"REQUEST\n\n\nLady Suzanne  10 Minutes JOI Game.mp4\n\n\nScreens \n    &lt;a href=&quot;\nhttp://image.bayimg.com/f2fb54f6e22a59f89819c95ecf669a125474810e.jpg&quot; rel=&quot;nofollow&quot; target=&quot;_NEW&quot;&gt;\nhttp://image.bayimg.com/f2fb54f6e22a59f89819c95ecf669a125474810e.jpg&lt;/a&gt;\n\n\n14 000 down, but how much more to come ?? You decide ;) \n\nThe more you appreciate it, the more we want to do it. Can we get to 15k ??? \n\nWell, if you still like what Shallow2 and I upload, how about leaving us a nice comment below ? :)\n\n\nAny Questions ?? Read our FAQ!!\n      &lt;a href=&quot;\nhttp://image.bayimg.com/eaea7e9e982a9a677d61e4f5aaf93b7643bd6eeb.jpg&quot; rel=&quot;nofollow&quot; target=&quot;_NEW&quot;&gt;\nhttp://image.bayimg.com/eaea7e9e982a9a677d61e4f5aaf93b7643bd6eeb.jpg&lt;/a&gt;\n\n\nCheers  :-) ","torrent":{"xt":"urn:btih:2d9b8067d85436630616af33ce778bc67c4bc0f0","amp;dn":"Lady+Suzanne%5C----10+Minutes+JOI+Game.mp4","amp;tr":["udp%3A%2F%2Ftracker.openbittorrent.com%3A80","udp%3A%2F%2Fopen.demonii.com%3A1337","udp%3A%2F%2Ftracker.coppersurfer.tk%3A6969","udp%3A%2F%2Fexodus.desync.com%3A6969"],"infoHash":"2d9b8067d85436630616af33ce778bc67c4bc0f0","infoHashBuffer":{"type":"Buffer","data":[45,155,128,103,216,84,54,99,6,22,175,51,206,119,139,198,124,75,192,240]},"announce":[],"urlList":[]}}