{"title":"A Bible Believer Looks At World History - Frederick Widdowson","uid":11773460,"size":12231469,"categoryP":"other","categoryS":"e_books","magnet":"?xt=urn:btih:3d3152a2020eaf9a1ca5243894d457bd77360183&amp;dn=A+Bible+Believer+Looks+At+World+History+-+Frederick+Widdowson&amp;tr=udp%3A%2F%2Ftracker.openbittorrent.com%3A80&amp;tr=udp%3A%2F%2Fopen.demonii.com%3A1337&amp;tr=udp%3A%2F%2Ftracker.coppersurfer.tk%3A6969&amp;tr=udp%3A%2F%2Fexodus.desync.com%3A6969","seeders":2,"leechers":0,"uploader":"starxteel","files":1,"time":1427168722,"description":"\nThis is a review of world history from a Bible believer's perspective from the beginning through World War Two. It is designed for use by homeschoolers but anyone can learn from it. Each chapter has a list of study questions and a sample quiz taken from those questions. These are the basics of World History up to the Second World War.\n\n\nAbout the author:\nFrederick Widdowson is a 59 year old grandfather who teaches boxing and kickboxing at a local boxing club. He haa a Masters Degree in American History from American Public University. He's currently studying Ancient and Classical History through American Military University.\n\nFor several years he taught home-schooled children as a tutor in World History, American History, and Civics. Not able to find any textbooks that he felt gave the Bible its proper due he has written his own.\n\nMost importantly he is a Bible Believing Christian who has read the King James Bible through 59 times. Fred and his amazing wife, Beth, live near Gettysburg, Pa","torrent":{"xt":"urn:btih:3d3152a2020eaf9a1ca5243894d457bd77360183","amp;dn":"A+Bible+Believer+Looks+At+World+History+-+Frederick+Widdowson","amp;tr":["udp%3A%2F%2Ftracker.openbittorrent.com%3A80","udp%3A%2F%2Fopen.demonii.com%3A1337","udp%3A%2F%2Ftracker.coppersurfer.tk%3A6969","udp%3A%2F%2Fexodus.desync.com%3A6969"],"infoHash":"3d3152a2020eaf9a1ca5243894d457bd77360183","infoHashBuffer":{"type":"Buffer","data":[61,49,82,162,2,14,175,154,28,165,36,56,148,212,87,189,119,54,1,131]},"announce":[],"urlList":[]}}