{"title":"Japanese Homemade.wmv","uid":9519871,"size":321297064,"categoryP":"porn","categoryS":"movie_clips","magnet":"?xt=urn:btih:619a5a140c4c7f9892ed7dcb61d6c81446e84964&amp;dn=Japanese+Homemade.wmv&amp;tr=udp%3A%2F%2Ftracker.openbittorrent.com%3A80&amp;tr=udp%3A%2F%2Fopen.demonii.com%3A1337&amp;tr=udp%3A%2F%2Ftracker.coppersurfer.tk%3A6969&amp;tr=udp%3A%2F%2Fexodus.desync.com%3A6969","seeders":3,"leechers":0,"uploader":"Pornmaze","files":-1,"time":1390607246,"description":"Japanese Homemade.wmv\n\n2014, Homemade, Teen, Asian, Japanese, 1on1, All sex, Oral, Hardcore, Teen, XXX, Adult\n\n640 x 480\n\n00:32:01\n\n306.41 MB\n\nScreens\n &lt;a href=&quot;\nhttp://www.pixsor.com/share-ABE9_52E2EC38.html&quot; rel=&quot;nofollow&quot; target=&quot;_NEW&quot;&gt;\nhttp://www.pixsor.com/share-ABE9_52E2EC38.html&lt;/a&gt;\n &lt;a href=&quot;\nhttp://www.pixsor.com/share-14F5_52E2EC39.html&quot; rel=&quot;nofollow&quot; target=&quot;_NEW&quot;&gt;\nhttp://www.pixsor.com/share-14F5_52E2EC39.html&lt;/a&gt;","torrent":{"xt":"urn:btih:619a5a140c4c7f9892ed7dcb61d6c81446e84964","amp;dn":"Japanese+Homemade.wmv","amp;tr":["udp%3A%2F%2Ftracker.openbittorrent.com%3A80","udp%3A%2F%2Fopen.demonii.com%3A1337","udp%3A%2F%2Ftracker.coppersurfer.tk%3A6969","udp%3A%2F%2Fexodus.desync.com%3A6969"],"infoHash":"619a5a140c4c7f9892ed7dcb61d6c81446e84964","infoHashBuffer":{"type":"Buffer","data":[97,154,90,20,12,76,127,152,146,237,125,203,97,214,200,20,70,232,73,100]},"announce":[],"urlList":[]}}