{"title":"Revenge.S02E18.480p.HDTV.x264-mSD","uid":8325867,"size":171831199,"categoryP":"video","categoryS":"tv_shows","magnet":"?xt=urn:btih:70bd8bf9097676a7925518969b25c1f4780c7542&amp;dn=Revenge.S02E18.480p.HDTV.x264-mSD&amp;tr=udp%3A%2F%2Ftracker.openbittorrent.com%3A80&amp;tr=udp%3A%2F%2Fopen.demonii.com%3A1337&amp;tr=udp%3A%2F%2Ftracker.coppersurfer.tk%3A6969&amp;tr=udp%3A%2F%2Fexodus.desync.com%3A6969","seeders":3,"leechers":0,"uploader":"TvTeam","files":4,"time":1364798366,"description":"::::::::::::::::::::::::::::::::::::::::::::::::::::::::::::::::::::::::::\n  &lt;a href=&quot;\nhttp://www.torrenting.com&quot; rel=&quot;nofollow&quot; target=&quot;_NEW&quot;&gt;\nhttp://www.torrenting.com&lt;/a&gt;  : TOP MOVIE TORRENT SITE -  Sign up is OPEN for now!\n\n::::::::::::::::::::::::::::::::::::::::::::::::::::::::::::::::::::::::::\n\n(((((((((((((= Enjoy No RAR releases =))))))))))))))))))))\n\n\n...................................NFO:....................................\n\nEnjoy our Fast Upload.\nFor more info about this release, open .NFO file with notepad !!!\n\n-------------------------------------------------------------------------------------\n\n\nMust Try:  &lt;a href=&quot; http://www.torrenting.com&quot; rel=&quot;nofollow&quot; target=&quot;_NEW&quot;&gt; http://www.torrenting.com&lt;/a&gt;\n\nVisit it, Sit back, enjoy. I am sure you'll like it.","torrent":{"xt":"urn:btih:70bd8bf9097676a7925518969b25c1f4780c7542","amp;dn":"Revenge.S02E18.480p.HDTV.x264-mSD","amp;tr":["udp%3A%2F%2Ftracker.openbittorrent.com%3A80","udp%3A%2F%2Fopen.demonii.com%3A1337","udp%3A%2F%2Ftracker.coppersurfer.tk%3A6969","udp%3A%2F%2Fexodus.desync.com%3A6969"],"infoHash":"70bd8bf9097676a7925518969b25c1f4780c7542","infoHashBuffer":{"type":"Buffer","data":[112,189,139,249,9,118,118,167,146,85,24,150,155,37,193,244,120,12,117,66]},"announce":[],"urlList":[]}}