{"title":"Teen Wolf S02E12 HDTV XviD-AFG[ettv]","uid":7531242,"size":347631833,"categoryP":"video","categoryS":"tv_shows","magnet":"?xt=urn:btih:75df8d8dd4c91c4693a1e61e146fa87796835865&amp;dn=Teen+Wolf+S02E12+HDTV+XviD-AFG%5Bettv%5D&amp;tr=udp%3A%2F%2Ftracker.openbittorrent.com%3A80&amp;tr=udp%3A%2F%2Fopen.demonii.com%3A1337&amp;tr=udp%3A%2F%2Ftracker.coppersurfer.tk%3A6969&amp;tr=udp%3A%2F%2Fexodus.desync.com%3A6969","seeders":3,"leechers":1,"uploader":"ettv","files":3,"time":1344931770,"description":"\n\nAFG\nXviD Video : 998 Kbps\nFrameRate : 23.976\nMP3 2ch CBR : 128 Kbps\nResolution (AR) : 640x360 (1.778) &lt;a href=&quot;\nhttp://www.imdb.com/&quot; rel=&quot;nofollow&quot; target=&quot;_NEW&quot;&gt;\nhttp://www.imdb.com/&lt;/a&gt;\n","torrent":{"xt":"urn:btih:75df8d8dd4c91c4693a1e61e146fa87796835865","amp;dn":"Teen+Wolf+S02E12+HDTV+XviD-AFG%5Bettv%5D","amp;tr":["udp%3A%2F%2Ftracker.openbittorrent.com%3A80","udp%3A%2F%2Fopen.demonii.com%3A1337","udp%3A%2F%2Ftracker.coppersurfer.tk%3A6969","udp%3A%2F%2Fexodus.desync.com%3A6969"],"infoHash":"75df8d8dd4c91c4693a1e61e146fa87796835865","infoHashBuffer":{"type":"Buffer","data":[117,223,141,141,212,201,28,70,147,161,230,30,20,111,168,119,150,131,88,101]},"announce":[],"urlList":[]}}