{"title":"M. Jackson - Thriller - Japan 12 inch single [Flac 96kHz] - Viny","uid":7006481,"size":256813401,"categoryP":"audio","categoryS":"flac","magnet":"?xt=urn:btih:879dbbdc1601d5857196f302c429c16e042c71de&amp;dn=M.+Jackson+-+Thriller+-+Japan+12+inch+single+%5BFlac+96kHz%5D+-+Viny&amp;tr=udp%3A%2F%2Ftracker.openbittorrent.com%3A80&amp;tr=udp%3A%2F%2Fopen.demonii.com%3A1337&amp;tr=udp%3A%2F%2Ftracker.coppersurfer.tk%3A6969&amp;tr=udp%3A%2F%2Fexodus.desync.com%3A6969","seeders":2,"leechers":0,"uploader":"F.C.M.","files":-1,"time":1328287193,"description":"Thriller 12&quot; single [Japan pressing]\n\nA1 - Thriller\nB1 - Thriller (instrumental)\n\n--------\n\nRecord in mint condition!\n\nWe all know the song Thriller, but this instrumental version is amazing. It is full of sounds that you can hardly hear in the vocal version. Pay attention to the bridge and the bass  :o \n\nAT 440MLa cartridge\nPro-Ject Debut III Esprit (White) turntable \nSony TA-v925EE preamp\nAdobe Audition CS5.5 recording software\n\nMore details in Rip info.txt file\n\nHope you like it. Enjoy!  ;) ","torrent":{"xt":"urn:btih:879dbbdc1601d5857196f302c429c16e042c71de","amp;dn":"M.+Jackson+-+Thriller+-+Japan+12+inch+single+%5BFlac+96kHz%5D+-+Viny","amp;tr":["udp%3A%2F%2Ftracker.openbittorrent.com%3A80","udp%3A%2F%2Fopen.demonii.com%3A1337","udp%3A%2F%2Ftracker.coppersurfer.tk%3A6969","udp%3A%2F%2Fexodus.desync.com%3A6969"],"infoHash":"879dbbdc1601d5857196f302c429c16e042c71de","infoHashBuffer":{"type":"Buffer","data":[135,157,187,220,22,1,213,133,113,150,243,2,196,41,193,110,4,44,113,222]},"announce":[],"urlList":[]}}