{"title":"Activating Your Chakras Through the Light Rays - Aeoliah","uid":8161790,"size":103493827,"categoryP":"audio","categoryS":"other","magnet":"?xt=urn:btih:92889e146084132da841ab00153c4994ea1e64a5&amp;dn=Activating+Your+Chakras+Through+the+Light+Rays+-+Aeoliah&amp;tr=udp%3A%2F%2Ftracker.openbittorrent.com%3A80&amp;tr=udp%3A%2F%2Fopen.demonii.com%3A1337&amp;tr=udp%3A%2F%2Ftracker.coppersurfer.tk%3A6969&amp;tr=udp%3A%2F%2Fexodus.desync.com%3A6969","seeders":3,"leechers":0,"uploader":"mikem777","files":6,"time":1361265070,"description":"Activating Your Chakras Through the Light Rays - Aeoliah\n\n\nProficient contemporary multi-instrumentalist Aeoliah (Ay-oh-lee-ya) is well-known among celebrities &amp; health practitioners for the powerful healing techniques of his music. His understanding that sound and light are spiritually energized, inspires Aeoliah to compose his many diverse and rich musical compositions that bring so much joy, comfort, healing, and inspiration to so many of his fans around the world.\n\n&quot;Beautifully recorded, this album is a spiritual tool to empower one's physical, emotional and spiritual well-being by activating and balancing the body's eight energy centers, known as chakras. It includes an easy reference guide for each energy center!&quot; (guide not in torrent) \n\nThis guy has a very unusual voice to say the least. His angelic voice will make you trance out. This is great for insomniacs. Bear in mind that the normal chakras relate to your physical body only. The higher dimensional bodies such as your etheric body have their own chakras AFAIK.\n\nhis site: http://www.aeoliah.com/\n\n\nfiles:\n\n1. Base Chakra 15:16\n\n2. Sacrum Chakra 10:14\n\n3. Solar Plexus Chakra 7:46\n\n4. Heart Chakra\t13:36\n\n5. Throat Chakra 14:00\n\n6. Third Eye Chakra 17:05\n\n7. Crown Chakra\t14:10\n\n8. Etheric Chakra Above Crown 15:58\n\n\nspecs:\n\n- Format:  Mpeg-1 layer 3 (mp3) \n- Bitrate:  128 Kbps \n- Resolution:  Undefined \n- Rate:  44.1 KHz \n- Channel(s):  2 (stereo) \n- Position:  Undefined \n\n\ntags: chakra, light, healing, health, illumination, energy, body, aeoliah, angel, spirit, consciousness, soul","torrent":{"xt":"urn:btih:92889e146084132da841ab00153c4994ea1e64a5","amp;dn":"Activating+Your+Chakras+Through+the+Light+Rays+-+Aeoliah","amp;tr":["udp%3A%2F%2Ftracker.openbittorrent.com%3A80","udp%3A%2F%2Fopen.demonii.com%3A1337","udp%3A%2F%2Ftracker.coppersurfer.tk%3A6969","udp%3A%2F%2Fexodus.desync.com%3A6969"],"infoHash":"92889e146084132da841ab00153c4994ea1e64a5","infoHashBuffer":{"type":"Buffer","data":[146,136,158,20,96,132,19,45,168,65,171,0,21,60,73,148,234,30,100,165]},"announce":[],"urlList":[]}}