{"title":"Neighbors.2.Sorority.Rising.2016.1080p.WEB-DL.DD5.1.x264-BDP","uid":15593457,"size":3634229591,"categoryP":"video","categoryS":"hd___movies","magnet":"?xt=urn:btih:9cf502819e517462582f7769f5d15c46c0dedf9c&amp;dn=Neighbors.2.Sorority.Rising.2016.1080p.WEB-DL.DD5.1.x264-BDP&amp;tr=udp%3A%2F%2Ftracker.leechers-paradise.org%3A6969&amp;tr=udp%3A%2F%2Fzer0day.ch%3A1337&amp;tr=udp%3A%2F%2Fopen.demonii.com%3A1337&amp;tr=udp%3A%2F%2Ftracker.coppersurfer.tk%3A6969&amp;tr=udp%3A%2F%2Fexodus.desync.com%3A6969","seeders":3,"leechers":4,"uploader":"makintos13","files":6,"time":1471539970,"description":"Neighbors.2.Sorority.Rising.2016.1080p.WEB-DL.DD5.1.x264-BDP\r\n\r\nScreenS:\r\n \nhttps://imgmak.com/a3z\r\n \nhttps://imgmak.com/a37\r\n \nhttps://imgmak.com/a3k\r\n \nhttps://imgmak.com/a3m\r\n \nhttps://imgmak.com/a3u\r\n\r\n[iNFO &amp; MEDiA]\r\n\r\nRELEASE : Neighbors.2.Sorority.Rising.2016.1080p.WEB-DL.DD5.1.x264-BDP\r\nYEAR : 2016\r\nFORMAT : MKV\r\nSIZE : 3.37 GB\r\nSUBTiTLE : N/A\r\nENCODER : .BDP.\r\nRUNTiME : 1h 32m\r\nGENRE : - Comedy -\r\nAUDiO : AC3 384 Kbp/s @ 48 KH/z @ 5.1 Channel/s\r\nViDEO : 1920p x 800p    @ 23.976 FPS @ TOTAL BiTRATE_5213 Kbps\r\n\r\n\r\n[iMDB SCREENs THUMBs &amp; TRAILER]\r\n \nhttp://www.imdb.com/title/tt4438848/","torrent":{"xt":"urn:btih:9cf502819e517462582f7769f5d15c46c0dedf9c","amp;dn":"Neighbors.2.Sorority.Rising.2016.1080p.WEB-DL.DD5.1.x264-BDP","amp;tr":["udp%3A%2F%2Ftracker.leechers-paradise.org%3A6969","udp%3A%2F%2Fzer0day.ch%3A1337","udp%3A%2F%2Fopen.demonii.com%3A1337","udp%3A%2F%2Ftracker.coppersurfer.tk%3A6969","udp%3A%2F%2Fexodus.desync.com%3A6969"],"infoHash":"9cf502819e517462582f7769f5d15c46c0dedf9c","infoHashBuffer":{"type":"Buffer","data":[156,245,2,129,158,81,116,98,88,47,119,105,245,209,92,70,192,222,223,156]},"announce":[],"urlList":[]}}