{"title":"[Tuts Plus] The Fundamentals of Background Art for Video Games V","uid":11404292,"size":1557650279,"categoryP":"video","categoryS":"other","magnet":"?xt=urn:btih:bc01cf912d21cbc260f4803bee5cb03f1ca99053&amp;dn=%5BTuts+Plus%5D+The+Fundamentals+of+Background+Art+for+Video+Games+V&amp;tr=udp%3A%2F%2Ftracker.openbittorrent.com%3A80&amp;tr=udp%3A%2F%2Fopen.demonii.com%3A1337&amp;tr=udp%3A%2F%2Ftracker.coppersurfer.tk%3A6969&amp;tr=udp%3A%2F%2Fexodus.desync.com%3A6969","seeders":2,"leechers":2,"uploader":"xKTRx","files":24,"time":1415458229,"description":"[Tuts Plus] The Fundamentals of Background Art for Video Games Video Tutorial-KTR\n\n\nPUBLISHER....: Tuts Plus\nLANGUAGE......: ENGLISH \nAUTHOR.......: Gary Simon\nRUNTIME......: 2.4 hours\nSOFTWARE.....: Adobe Illustrator\n\n\nAbout this course::\n\nOne of the most important aspects of a successful video game is the environment. The background is what sets the stage for the player, and knowing how to create great-looking backgrounds will improve your value as a designer. We will take a look at basic game design concepts, and then design two tileable game backgrounds using Adobe Illustrator.\n\n\nTopics include:\n\n1.Introduction\n1.1Introduction\n\n2.Basic Game Design Concepts\n2.1Environment Design Basics\n2.2Tiling Background Design\n2.3Vector vs. Non-Vector\n\n3.Project 1: Jungle Side Scrolling Background\n3.1Document Setup and Mountain Design\n3.2Ground Design\n3.3Designing the Trees\n3.4Final Details\n3.5Jungle Background: Optional Assignment\n\n\n4.Project 2: Haunted House Scrolling Background\n4.1Document Setup and Background Design\n4.2Midground Design\n4.3Street Design\n4.4Haunted House Design\n4.5Adding More Houses\n4.6Final Touches\n4.7Haunted House: Optional Assignment\n\n\n5.Closing\n5.1Course Overview","torrent":{"xt":"urn:btih:bc01cf912d21cbc260f4803bee5cb03f1ca99053","amp;dn":"%5BTuts+Plus%5D+The+Fundamentals+of+Background+Art+for+Video+Games+V","amp;tr":["udp%3A%2F%2Ftracker.openbittorrent.com%3A80","udp%3A%2F%2Fopen.demonii.com%3A1337","udp%3A%2F%2Ftracker.coppersurfer.tk%3A6969","udp%3A%2F%2Fexodus.desync.com%3A6969"],"infoHash":"bc01cf912d21cbc260f4803bee5cb03f1ca99053","infoHashBuffer":{"type":"Buffer","data":[188,1,207,145,45,33,203,194,96,244,128,59,238,92,176,63,28,169,144,83]},"announce":[],"urlList":[]}}