{"title":"The Soft Bulletin - The Flaming Lips (Complete/FLAC)","uid":10093324,"size":696670311,"categoryP":"audio","categoryS":"flac","magnet":"?xt=urn:btih:c2650817d2312a83bd03f3f2b33a1f68aa9aa0b2&amp;dn=The+Soft+Bulletin+-+The+Flaming+Lips+%28Complete%2FFLAC%29&amp;tr=udp%3A%2F%2Ftracker.openbittorrent.com%3A80&amp;tr=udp%3A%2F%2Fopen.demonii.com%3A1337&amp;tr=udp%3A%2F%2Ftracker.coppersurfer.tk%3A6969&amp;tr=udp%3A%2F%2Fexodus.desync.com%3A6969","seeders":2,"leechers":1,"uploader":null,"files":-1,"time":1399243597,"description":"The Soft Bulletin\nThe Flaming Lips (1999)\n\n16 bit / 44.1 khz FLAC\n\nComplete Edition\n\n--------------------------------------------\n\nAfter scouring the internet for every version of every track on the Soft Bulletin, here it is in lossless glory. The first disc contains the mixes the Flaming Lips themselves created in the order that they originally intended. This combines tracks from the US and UK CD releases, and is identical to the tracks and order found on the vinyl release. Disc 2 contains the remixes that Warner Bros. commissioned for the potential singles, mixed by Peter Mokran. \n\n--------------------------------------------\n\n\nDisc 1\n\n1. Race for the Prize\n2. A Spoonful Weighs a Ton\n3. The Spark that Bled\n4. The Spiderbite Song\n5. Buggin'\n6. What is the Light??\n7. The Observer\n8. Waitin' for a Superman\n9. Suddenly Everything Has Changed\n10. The Gash\n11. Slow Motion\n12. Feeling Yourself Disintegrate\n13. Sleeping on the Roof\n\nDisc 2 (Peter Mokran Remixes)\n\n1. Race for the Prize (Remix)\n2. Waitin' for a Superman (Remix)\n3. Buggin' (Remix)\n\n\n\n","torrent":{"xt":"urn:btih:c2650817d2312a83bd03f3f2b33a1f68aa9aa0b2","amp;dn":"The+Soft+Bulletin+-+The+Flaming+Lips+%28Complete%2FFLAC%29","amp;tr":["udp%3A%2F%2Ftracker.openbittorrent.com%3A80","udp%3A%2F%2Fopen.demonii.com%3A1337","udp%3A%2F%2Ftracker.coppersurfer.tk%3A6969","udp%3A%2F%2Fexodus.desync.com%3A6969"],"infoHash":"c2650817d2312a83bd03f3f2b33a1f68aa9aa0b2","infoHashBuffer":{"type":"Buffer","data":[194,101,8,23,210,49,42,131,189,3,243,242,179,58,31,104,170,154,160,178]},"announce":[],"urlList":[]}}