{"title":"The.Marine.3.2013.STV.DVDRip.XviD-SCAD","uid":8199185,"size":734201337,"categoryP":"video","categoryS":"movies","magnet":"?xt=urn:btih:c8cfce435bb18cfdab4744ce80c3eff10cbaf2b0&amp;dn=The.Marine.3.2013.STV.DVDRip.XviD-SCAD&amp;tr=udp%3A%2F%2Ftracker.openbittorrent.com%3A80&amp;tr=udp%3A%2F%2Fopen.demonii.com%3A1337&amp;tr=udp%3A%2F%2Ftracker.coppersurfer.tk%3A6969&amp;tr=udp%3A%2F%2Fexodus.desync.com%3A6969","seeders":2,"leechers":0,"uploader":"sceneline","files":53,"time":1361980851,"description":"- &lt;a href=&quot;\nhttp://www.Speed.Cd&quot; rel=&quot;nofollow&quot; target=&quot;_NEW&quot;&gt;\nhttp://www.Speed.Cd&lt;/a&gt;\n &lt;a href=&quot;\nhttp://www.Speed.Cd&quot; rel=&quot;nofollow&quot; target=&quot;_NEW&quot;&gt;\nhttp://www.Speed.Cd&lt;/a&gt;       the fast  and The Hottest Private Tracker on the net\n\nPlease Seed back to make the speed Faster!!\n ............ NFO .............\n-\n        \n        \n                  \n                 \n                          \n                      \n        \n\n\n\n \n  #Presents\n \n  The Marine 3: Homefront (2013)\n\n  .     Imdb ]--[ http://www.imdb.com/title/tt2334841/      \n  .    Genre ]--[ Action    \n  .   Rating ]--[ - /10 (0 votes)                    \n  .  Runtime ]--[ 86 min                                   \n  . Rls.Date ]--[ 27/02/2013                \n\n\n                                               \n  #Release Info\n\n  .     Video ]--[ 945 kbps xvid\n  .     Audio ]--[ 128 kbps mp3 vbr\n  . Resolution]--[ 640x272 @ 23.976fps\n  .     Discs ]--[ 1 \n  .      Subs ]--[ None\n\n\n\n  #Release Notes\n  \n\n\n\n\n  #Group Info\n\n\n  We are currently looking for:\n  . 100Mbit+ affil sites \n  . Pre-Retail DVD suppliers\n  \n  Greetings:\n  . Mom and Dad\n\n  Contact:\n  . Find Us","torrent":{"xt":"urn:btih:c8cfce435bb18cfdab4744ce80c3eff10cbaf2b0","amp;dn":"The.Marine.3.2013.STV.DVDRip.XviD-SCAD","amp;tr":["udp%3A%2F%2Ftracker.openbittorrent.com%3A80","udp%3A%2F%2Fopen.demonii.com%3A1337","udp%3A%2F%2Ftracker.coppersurfer.tk%3A6969","udp%3A%2F%2Fexodus.desync.com%3A6969"],"infoHash":"c8cfce435bb18cfdab4744ce80c3eff10cbaf2b0","infoHashBuffer":{"type":"Buffer","data":[200,207,206,67,91,177,140,253,171,71,68,206,128,195,239,241,12,186,242,176]},"announce":[],"urlList":[]}}