{"title":"De Jeugd van Tegenwoordig - De Lachende Derde Gold Edition","uid":6906120,"size":88531653,"categoryP":"audio","categoryS":"music","magnet":"?xt=urn:btih:cb2b649675b014dc99b2b96cd2de0d49cf23cb45&amp;dn=De+Jeugd+van+Tegenwoordig+-+De+Lachende+Derde+Gold+Edition&amp;tr=udp%3A%2F%2Ftracker.openbittorrent.com%3A80&amp;tr=udp%3A%2F%2Fopen.demonii.com%3A1337&amp;tr=udp%3A%2F%2Ftracker.coppersurfer.tk%3A6969&amp;tr=udp%3A%2F%2Fexodus.desync.com%3A6969","seeders":2,"leechers":0,"uploader":"joeriiee","files":11,"time":1324591775,"description":"Dit is de bonus CD van het album De Lachende Derde van de Jeugd van Tegenwoordig.\n\n320kbps\n\nEnjoy!","torrent":{"xt":"urn:btih:cb2b649675b014dc99b2b96cd2de0d49cf23cb45","amp;dn":"De+Jeugd+van+Tegenwoordig+-+De+Lachende+Derde+Gold+Edition","amp;tr":["udp%3A%2F%2Ftracker.openbittorrent.com%3A80","udp%3A%2F%2Fopen.demonii.com%3A1337","udp%3A%2F%2Ftracker.coppersurfer.tk%3A6969","udp%3A%2F%2Fexodus.desync.com%3A6969"],"infoHash":"cb2b649675b014dc99b2b96cd2de0d49cf23cb45","infoHashBuffer":{"type":"Buffer","data":[203,43,100,150,117,176,20,220,153,178,185,108,210,222,13,73,207,35,203,69]},"announce":[],"urlList":[]}}