{"title":"[Commie] Space Dandy - 08 [F1A2DF6A].mkv","uid":9683203,"size":602506707,"categoryP":"video","categoryS":"hd___tv_shows","magnet":"?xt=urn:btih:cb4bdbc5946392fc7fb57006d49c85af8d7c8401&amp;dn=%5BCommie%5D+Space+Dandy+-+08+%5BF1A2DF6A%5D.mkv&amp;tr=udp%3A%2F%2Ftracker.openbittorrent.com%3A80&amp;tr=udp%3A%2F%2Fopen.demonii.com%3A1337&amp;tr=udp%3A%2F%2Ftracker.coppersurfer.tk%3A6969&amp;tr=udp%3A%2F%2Fexodus.desync.com%3A6969","seeders":2,"leechers":1,"uploader":"darkj6","files":1,"time":1393703334,"description":" ______   _______  ______    ___   _      ___  --------|\n|      | |   _   ||    _ |  |   | | |    |   ||   |----|    \n|  _    ||  |_|  ||   | ||  |   |_| |    |   ||   |___ \n| | |   ||       ||   |_||_ |      _|    |   ||    _  |\n| |_|   ||       ||    __  ||     |_  ___|   ||   | | |\n|       ||   _   ||   |  | ||    _  ||       ||   |_| |\n|______| |__| |__||___|  |_||___| |_||_______||_______|\t","torrent":{"xt":"urn:btih:cb4bdbc5946392fc7fb57006d49c85af8d7c8401","amp;dn":"%5BCommie%5D+Space+Dandy+-+08+%5BF1A2DF6A%5D.mkv","amp;tr":["udp%3A%2F%2Ftracker.openbittorrent.com%3A80","udp%3A%2F%2Fopen.demonii.com%3A1337","udp%3A%2F%2Ftracker.coppersurfer.tk%3A6969","udp%3A%2F%2Fexodus.desync.com%3A6969"],"infoHash":"cb4bdbc5946392fc7fb57006d49c85af8d7c8401","infoHashBuffer":{"type":"Buffer","data":[203,75,219,197,148,99,146,252,127,181,112,6,212,156,133,175,141,124,132,1]},"announce":[],"urlList":[]}}