{"title":"Modern Times 1936 Special Edition 720p BluRay DTS x264-HDViE BOZ","uid":6031119,"size":6375180459,"categoryP":"video","categoryS":"hd___movies","magnet":"?xt=urn:btih:d83eaa0330315e67c53a56debf9a322c33172a3e&amp;dn=Modern+Times+1936+Special+Edition+720p+BluRay+DTS+x264-HDViE+BOZ&amp;tr=udp%3A%2F%2Ftracker.openbittorrent.com%3A80&amp;tr=udp%3A%2F%2Fopen.demonii.com%3A1337&amp;tr=udp%3A%2F%2Ftracker.coppersurfer.tk%3A6969&amp;tr=udp%3A%2F%2Fexodus.desync.com%3A6969","seeders":2,"leechers":0,"uploader":"BOZX","files":-1,"time":1292086091,"description":"Modern Times Blu-ray special edition made from the telecine with 2K-HD resolution,\nfor much better quality Blu-ray old versions.\n\n\nQuote:\nM O D E R N  T I M E S\n----------------------\nDescription Original Title: Modern Times\nReleased Year.............: 1936\nGenre.....................: Comedy | Drama | Romance\nImdb Link.................: &lt;a href=&quot; http://www.imdb.com/title/tt0027977/&quot; rel=&quot;nofollow&quot; target=&quot;_NEW&quot;&gt; http://www.imdb.com/title/tt0027977/&lt;/a&gt;\nSource....................: BluRay Criterion Collection AVC 1080p PCM1.0\n\nHDViE RELEASED iNFO\n-------------------\nCONTAiNER...........: Matroska\nRUN TiME............: 87 min\nFiLE SiZE...........: 5.93 GiB\n\nViDEO ENCODER.......: x264\nBiRATE..............: 9.2 Mbps\nFRAME RATE..........: 23.976 fps\nFRAME SiZE..........: 960x720\n\nAUDiO CODEC.........: DTS\nBiRATE..............: 512 Kbps\nCHANEL..............: 1CH (Mono)\nLANGUAGE............: English\n\nSUBTiTLE............: English | Vietnamese\nCHAPTERS............: Yes\nDXVA compliant......: Yes\n--------------------\nENCODER.............: TQN\n\nScreens :\n\n &lt;a href=&quot; http://www.phyrefile.com/image/view/LUWBnKMiMN9oFS80&quot; rel=&quot;nofollow&quot; target=&quot;_NEW&quot;&gt; http://www.phyrefile.com/image/view/LUWBnKMiMN9oFS80&lt;/a&gt;\n &lt;a href=&quot; http://www.phyrefile.com/image/view/WH22hBa9pv5BwIxw&quot; rel=&quot;nofollow&quot; target=&quot;_NEW&quot;&gt; http://www.phyrefile.com/image/view/WH22hBa9pv5BwIxw&lt;/a&gt;\n &lt;a href=&quot; http://www.phyrefile.com/image/view/NMyHghxos9aoUHx2&quot; rel=&quot;nofollow&quot; target=&quot;_NEW&quot;&gt; http://www.phyrefile.com/image/view/NMyHghxos9aoUHx2&lt;/a&gt;\n &lt;a href=&quot; http://www.phyrefile.com/image/view/gaia5t3cwofQvxZE&quot; rel=&quot;nofollow&quot; target=&quot;_NEW&quot;&gt; http://www.phyrefile.com/image/view/gaia5t3cwofQvxZE&lt;/a&gt;\n &lt;a href=&quot; http://www.phyrefile.com/image/view/HyXIwfHjmYgMcf9I&quot; rel=&quot;nofollow&quot; target=&quot;_NEW&quot;&gt; http://www.phyrefile.com/image/view/HyXIwfHjmYgMcf9I&lt;/a&gt;\n &lt;a href=&quot; http://www.phyrefile.com/image/view/HyXIwfHjmYgMcf9I&quot; rel=&quot;nofollow&quot; target=&quot;_NEW&quot;&gt; http://www.phyrefile.com/image/view/HyXIwfHjmYgMcf9I&lt;/a&gt;\n &lt;a href=&quot; http://www.phyrefile.com/image/view/bJxqr7JIGGvAemkp&quot; rel=&quot;nofollow&quot; target=&quot;_NEW&quot;&gt; http://www.phyrefile.com/image/view/bJxqr7JIGGvAemkp&lt;/a&gt;\n &lt;a href=&quot; http://www.phyrefile.com/image/view/pzKB8khqIlnul8DG&quot; rel=&quot;nofollow&quot; target=&quot;_NEW&quot;&gt; http://www.phyrefile.com/image/view/pzKB8khqIlnul8DG&lt;/a&gt;","torrent":{"xt":"urn:btih:d83eaa0330315e67c53a56debf9a322c33172a3e","amp;dn":"Modern+Times+1936+Special+Edition+720p+BluRay+DTS+x264-HDViE+BOZ","amp;tr":["udp%3A%2F%2Ftracker.openbittorrent.com%3A80","udp%3A%2F%2Fopen.demonii.com%3A1337","udp%3A%2F%2Ftracker.coppersurfer.tk%3A6969","udp%3A%2F%2Fexodus.desync.com%3A6969"],"infoHash":"d83eaa0330315e67c53a56debf9a322c33172a3e","infoHashBuffer":{"type":"Buffer","data":[216,62,170,3,48,49,94,103,197,58,86,222,191,154,50,44,51,23,42,62]},"announce":[],"urlList":[]}}