{"title":"[Passion-hd] Nina North (Sensual Embrace/NEW **23.09.15 **) [.mp","uid":12475920,"size":350975887,"categoryP":"porn","categoryS":"movie_clips","magnet":"?xt=urn:btih:fa6f490ed89d9b1e785414af5ce8e7454275e1f6&amp;dn=%5BPassion-hd%5D+Nina+North+%28Sensual+Embrace%2FNEW+%2A%2A23.09.15+%2A%2A%29+%5B.mp&amp;tr=udp%3A%2F%2Ftracker.openbittorrent.com%3A80&amp;tr=udp%3A%2F%2Fopen.demonii.com%3A1337&amp;tr=udp%3A%2F%2Ftracker.coppersurfer.tk%3A6969&amp;tr=udp%3A%2F%2Fexodus.desync.com%3A6969","seeders":2,"leechers":6,"uploader":"Chinu685","files":1,"time":1442984183,"description":"[Passion-hd] Nina North (Sensual Embrace/NEW **23.09.15 **) [.mp4]\n &lt;a href=&quot;\nhttp://milfimage.org/img-5602159982277.html&quot; rel=&quot;nofollow&quot; target=&quot;_NEW&quot;&gt;\nhttp://milfimage.org/img-5602159982277.html&lt;/a&gt;\n &lt;a href=&quot;\nhttp://milfimage.org/img-5602159cacb6d.html&quot; rel=&quot;nofollow&quot; target=&quot;_NEW&quot;&gt;\nhttp://milfimage.org/img-5602159cacb6d.html&lt;/a&gt;\n &lt;a href=&quot;\nhttp://milfimage.org/img-560215a6a1f56.html&quot; rel=&quot;nofollow&quot; target=&quot;_NEW&quot;&gt;\nhttp://milfimage.org/img-560215a6a1f56.html&lt;/a&gt;\n\n\n\nâ—†â—†â—†..:For more awesome stuff please click below:..â—†â—†â—†\n                             &lt;a href=&quot;\nhttps://thepiratebay.la/user/Chinu685&quot; rel=&quot;nofollow&quot; target=&quot;_NEW&quot;&gt;\nhttps://thepiratebay.la/user/Chinu685&lt;/a&gt;","torrent":{"xt":"urn:btih:fa6f490ed89d9b1e785414af5ce8e7454275e1f6","amp;dn":"%5BPassion-hd%5D+Nina+North+%28Sensual+Embrace%2FNEW+%2A%2A23.09.15+%2A%2A%29+%5B.mp","amp;tr":["udp%3A%2F%2Ftracker.openbittorrent.com%3A80","udp%3A%2F%2Fopen.demonii.com%3A1337","udp%3A%2F%2Ftracker.coppersurfer.tk%3A6969","udp%3A%2F%2Fexodus.desync.com%3A6969"],"infoHash":"fa6f490ed89d9b1e785414af5ce8e7454275e1f6","infoHashBuffer":{"type":"Buffer","data":[250,111,73,14,216,157,155,30,120,84,20,175,92,232,231,69,66,117,225,246]},"announce":[],"urlList":[]}}